[
    {
        "problemName": "",
        "problemID": "",
        "problemStatus": "Incomplete",
        "problemTopic": "",
        "problemDifficulty": ""
    },
    {
        "problemName": "CHỌN Ô - 1",
        "problemLink": "https://code.ptit.edu.vn/student/question/DSA_P039",
        "problemID": "DSA_P039",
        "problemStatus": "Incomplete",
        "problemTopic": "Quy hoạch động",
        "problemDifficulty": "1"
    },
    {
        "problemName": "SỐ THỨ TỰ TỔ HỢP",
        "problemLink": "https://code.ptit.edu.vn/student/question/DSA01023",
        "problemID": "DSA01023",
        "problemStatus": "Incomplete",
        "problemTopic": "Sinh kế tiếp",
        "problemDifficulty": "1"
    },
    {
        "problemName": "ĐẶT TÊN - 1",
        "problemLink": "https://code.ptit.edu.vn/student/question/DSA01024",
        "problemID": "DSA01024",
        "problemStatus": "Incomplete",
        "problemTopic": "Quay lui - Nhánh cận",
        "problemDifficulty": "1"
    },
    {
        "problemName": "DÃY SỐ 1",
        "problemLink": "https://code.ptit.edu.vn/student/question/DSA02001",
        "problemID": "DSA02001",
        "problemStatus": "Incomplete",
        "problemTopic": "Quay lui - Nhánh cận",
        "problemDifficulty": "1"
    },
    {
        "problemName": "DI CHUYỂN TRONG MÊ CUNG 1",
        "problemLink": "https://code.ptit.edu.vn/student/question/DSA02003",
        "problemID": "DSA02003",
        "problemStatus": "Incomplete",
        "problemTopic": "Quay lui - Nhánh cận",
        "problemDifficulty": "1"
    },
    {
        "problemName": "HOÁN VỊ XÂU KÝ TỰ",
        "problemLink": "https://code.ptit.edu.vn/student/question/DSA02005",
        "problemID": "DSA02005",
        "problemStatus": "Incomplete",
        "problemTopic": "Quay lui - Nhánh cận",
        "problemDifficulty": "1"
    },
    {
        "problemName": "DI CHUYỂN TRONG MA TRẬN",
        "problemLink": "https://code.ptit.edu.vn/student/question/DSA02012",
        "problemID": "DSA02012",
        "problemStatus": "Incomplete",
        "problemTopic": "Quay lui - Nhánh cận",
        "problemDifficulty": "1"
    },
    {
        "problemName": "SẮP XẾP QUÂN HẬU 1",
        "problemLink": "https://code.ptit.edu.vn/student/question/DSA02016",
        "problemID": "DSA02016",
        "problemStatus": "Incomplete",
        "problemTopic": "Quay lui - Nhánh cận",
        "problemDifficulty": "1"
    },
    {
        "problemName": "THÁP HÀ NỘI",
        "problemLink": "https://code.ptit.edu.vn/student/question/DSA02029",
        "problemID": "DSA02029",
        "problemStatus": "Incomplete",
        "problemTopic": "Quay lui - Nhánh cận",
        "problemDifficulty": "1"
    },
    {
        "problemName": "LIỆT KÊ XÂU KÝ TỰ",
        "problemLink": "https://code.ptit.edu.vn/student/question/DSA02030",
        "problemID": "DSA02030",
        "problemStatus": "Incomplete",
        "problemTopic": "Quay lui - Nhánh cận",
        "problemDifficulty": "1"
    },
    {
        "problemName": "GHÉP CHỮ CÁI",
        "problemLink": "https://code.ptit.edu.vn/student/question/DSA02031",
        "problemID": "DSA02031",
        "problemStatus": "Incomplete",
        "problemTopic": "Quay lui - Nhánh cận",
        "problemDifficulty": "1"
    },
    {
        "problemName": "TRÒ CHƠI VỚI CÁC CON SỐ",
        "problemLink": "https://code.ptit.edu.vn/student/question/DSA02034",
        "problemID": "DSA02034",
        "problemStatus": "Incomplete",
        "problemTopic": "Quay lui - Nhánh cận",
        "problemDifficulty": "1"
    },
    {
        "problemName": "ĐỔI TIỀN",
        "problemLink": "https://code.ptit.edu.vn/student/question/DSA03001",
        "problemID": "DSA03001",
        "problemStatus": "Incomplete",
        "problemTopic": "Giải thuật tham lam",
        "problemDifficulty": "1"
    },
    {
        "problemName": "NHẦM CHỮ SỐ",
        "problemLink": "https://code.ptit.edu.vn/student/question/DSA03002",
        "problemID": "DSA03002",
        "problemStatus": "Incomplete",
        "problemTopic": "Giải thuật tham lam",
        "problemDifficulty": "1"
    },
    {
        "problemName": "TÌM MAX",
        "problemLink": "https://code.ptit.edu.vn/student/question/DSA03003",
        "problemID": "DSA03003",
        "problemStatus": "Incomplete",
        "problemTopic": "Giải thuật tham lam",
        "problemDifficulty": "1"
    },
    {
        "problemName": "TỔNG NHỎ NHẤT",
        "problemLink": "https://code.ptit.edu.vn/student/question/DSA03004",
        "problemID": "DSA03004",
        "problemStatus": "Incomplete",
        "problemTopic": "Giải thuật tham lam",
        "problemDifficulty": "1"
    },
    {
        "problemName": "SẮP XẾP CÔNG VIỆC 1",
        "problemLink": "https://code.ptit.edu.vn/student/question/DSA03008",
        "problemID": "DSA03008",
        "problemStatus": "Incomplete",
        "problemTopic": "Giải thuật tham lam",
        "problemDifficulty": "1"
    },
    {
        "problemName": "NỐI DÂY 1",
        "problemLink": "https://code.ptit.edu.vn/student/question/DSA03010",
        "problemID": "DSA03010",
        "problemStatus": "Incomplete",
        "problemTopic": "Giải thuật tham lam",
        "problemDifficulty": "1"
    },
    {
        "problemName": "SẮP ĐẶT XÂU KÝ TỰ 2",
        "problemLink": "https://code.ptit.edu.vn/student/question/DSA03013",
        "problemID": "DSA03013",
        "problemStatus": "Incomplete",
        "problemTopic": "Giải thuật tham lam",
        "problemDifficulty": "1"
    },
    {
        "problemName": "GẤP ĐÔI DÃY SỐ",
        "problemLink": "https://code.ptit.edu.vn/student/question/DSA04004",
        "problemID": "DSA04004",
        "problemStatus": "Incomplete",
        "problemTopic": "Chia và trị",
        "problemDifficulty": "1"
    },
    {
        "problemName": "DÃY CON LIÊN TIẾP CÓ TỔNG LỚN NHẤT",
        "problemLink": "https://code.ptit.edu.vn/student/question/DSA04010",
        "problemID": "DSA04010",
        "problemStatus": "Incomplete",
        "problemTopic": "Chia và trị",
        "problemDifficulty": "1"
    },
    {
        "problemName": "TÍNH FLOOR(X)",
        "problemLink": "https://code.ptit.edu.vn/student/question/DSA04015",
        "problemID": "DSA04015",
        "problemStatus": "Incomplete",
        "problemTopic": "Chia và trị",
        "problemDifficulty": "1"
    },
    {
        "problemName": "PHẦN TỬ KHÁC NHAU",
        "problemLink": "https://code.ptit.edu.vn/student/question/DSA04017",
        "problemID": "DSA04017",
        "problemStatus": "Incomplete",
        "problemTopic": "Chia và trị",
        "problemDifficulty": "1"
    },
    {
        "problemName": "ĐẾM SỐ 0",
        "problemLink": "https://code.ptit.edu.vn/student/question/DSA04018",
        "problemID": "DSA04018",
        "problemStatus": "Incomplete",
        "problemTopic": "Chia và trị",
        "problemDifficulty": "1"
    },
    {
        "problemName": "TÌM KIẾM NHỊ PHÂN",
        "problemLink": "https://code.ptit.edu.vn/student/question/DSA04020",
        "problemID": "DSA04020",
        "problemStatus": "Incomplete",
        "problemTopic": "Chia và trị",
        "problemDifficulty": "1"
    },
    {
        "problemName": "LŨY THỪA MA TRẬN 2",
        "problemLink": "https://code.ptit.edu.vn/student/question/DSA04024",
        "problemID": "DSA04024",
        "problemStatus": "Incomplete",
        "problemTopic": "Chia và trị",
        "problemDifficulty": "1"
    },
    {
        "problemName": "DÃY SỐ VÔ HẠN",
        "problemLink": "https://code.ptit.edu.vn/student/question/DSA04025",
        "problemID": "DSA04025",
        "problemStatus": "Incomplete",
        "problemTopic": "Chia và trị",
        "problemDifficulty": "1"
    },
    {
        "problemName": "XÂU CON CHUNG DÀI NHẤT",
        "problemLink": "https://code.ptit.edu.vn/student/question/DSA05001",
        "problemID": "DSA05001",
        "problemStatus": "Incomplete",
        "problemTopic": "Quy hoạch động",
        "problemDifficulty": "1"
    },
    {
        "problemName": "DÃY CON TĂNG DÀI NHẤT",
        "problemLink": "https://code.ptit.edu.vn/student/question/DSA05004",
        "problemID": "DSA05004",
        "problemStatus": "Incomplete",
        "problemTopic": "Quy hoạch động",
        "problemDifficulty": "1"
    },
    {
        "problemName": "SỐ BƯỚC ÍT NHẤT",
        "problemLink": "https://code.ptit.edu.vn/student/question/DSA05005",
        "problemID": "DSA05005",
        "problemStatus": "Incomplete",
        "problemTopic": "Quy hoạch động",
        "problemDifficulty": "1"
    },
    {
        "problemName": "DÃY CON CÓ TỔNG BẰNG S",
        "problemLink": "https://code.ptit.edu.vn/student/question/DSA05008",
        "problemID": "DSA05008",
        "problemStatus": "Incomplete",
        "problemTopic": "Quy hoạch động",
        "problemDifficulty": "1"
    },
    {
        "problemName": "TẬP CON BẰNG NHAU",
        "problemLink": "https://code.ptit.edu.vn/student/question/DSA05009",
        "problemID": "DSA05009",
        "problemStatus": "Incomplete",
        "problemTopic": "Quay lui - Nhánh cận",
        "problemDifficulty": "1"
    },
    {
        "problemName": "TỔ HỢP C(n, k)",
        "problemLink": "https://code.ptit.edu.vn/student/question/DSA05012",
        "problemID": "DSA05012",
        "problemStatus": "Incomplete",
        "problemTopic": "Quy hoạch động",
        "problemDifficulty": "1"
    },
    {
        "problemName": "CON ẾCH",
        "problemLink": "https://code.ptit.edu.vn/student/question/DSA05025",
        "problemID": "DSA05025",
        "problemStatus": "Incomplete",
        "problemTopic": "Quy hoạch động",
        "problemDifficulty": "1"
    },
    {
        "problemName": "XEM PHIM",
        "problemLink": "https://code.ptit.edu.vn/student/question/DSA05026",
        "problemID": "DSA05026",
        "problemStatus": "Incomplete",
        "problemTopic": "Quy hoạch động",
        "problemDifficulty": "1"
    },
    {
        "problemName": "CÁI TÚI",
        "problemLink": "https://code.ptit.edu.vn/student/question/DSA05027",
        "problemID": "DSA05027",
        "problemStatus": "Incomplete",
        "problemTopic": "Quy hoạch động",
        "problemDifficulty": "1"
    },
    {
        "problemName": "GIẢI MÃ",
        "problemLink": "https://code.ptit.edu.vn/student/question/DSA05029",
        "problemID": "DSA05029",
        "problemStatus": "Incomplete",
        "problemTopic": "Quy hoạch động",
        "problemDifficulty": "1"
    },
    {
        "problemName": "TỔNG SỐ CÁCH DI CHUYỂN",
        "problemLink": "https://code.ptit.edu.vn/student/question/DSA05034",
        "problemID": "DSA05034",
        "problemStatus": "Incomplete",
        "problemTopic": "Quy hoạch động",
        "problemDifficulty": "1"
    },
    {
        "problemName": "SẮP XẾP THEO GIÁ TRỊ TUYỆT ĐỐI",
        "problemLink": "https://code.ptit.edu.vn/student/question/DSA06002",
        "problemID": "DSA06002",
        "problemStatus": "Incomplete",
        "problemTopic": "Sắp xếp - Tìm kiếm",
        "problemDifficulty": "1"
    },
    {
        "problemName": "ĐỔI CHỖ ÍT NHẤT",
        "problemLink": "https://code.ptit.edu.vn/student/question/DSA06003",
        "problemID": "DSA06003",
        "problemStatus": "Incomplete",
        "problemTopic": "Sắp xếp - Tìm kiếm",
        "problemDifficulty": "1"
    },
    {
        "problemName": "CẶP SỐ TỔNG BẰNG K",
        "problemLink": "https://code.ptit.edu.vn/student/question/DSA06009",
        "problemID": "DSA06009",
        "problemStatus": "Incomplete",
        "problemTopic": "Sắp xếp - Tìm kiếm",
        "problemDifficulty": "1"
    },
    {
        "problemName": "SẮP XẾP CHỮ SỐ",
        "problemLink": "https://code.ptit.edu.vn/student/question/DSA06010",
        "problemID": "DSA06010",
        "problemStatus": "Incomplete",
        "problemTopic": "Sắp xếp - Tìm kiếm",
        "problemDifficulty": "1"
    },
    {
        "problemName": "TỔNG GẦN 0 NHẤT",
        "problemLink": "https://code.ptit.edu.vn/student/question/DSA06011",
        "problemID": "DSA06011",
        "problemStatus": "Incomplete",
        "problemTopic": "Sắp xếp - Tìm kiếm",
        "problemDifficulty": "1"
    },
    {
        "problemName": "TỔNG CẶP SỐ NGUYÊN TỐ",
        "problemLink": "https://code.ptit.edu.vn/student/question/DSA06014",
        "problemID": "DSA06014",
        "problemStatus": "Incomplete",
        "problemTopic": "Sắp xếp - Tìm kiếm",
        "problemDifficulty": "1"
    },
    {
        "problemName": "TÍCH LỚN NHẤT - NHỎ NHẤT",
        "problemLink": "https://code.ptit.edu.vn/student/question/DSA06016",
        "problemID": "DSA06016",
        "problemStatus": "Incomplete",
        "problemTopic": "Sắp xếp - Tìm kiếm",
        "problemDifficulty": "1"
    },
    {
        "problemName": "TRỘN HAI DÃY",
        "problemLink": "https://code.ptit.edu.vn/student/question/DSA06017",
        "problemID": "DSA06017",
        "problemStatus": "Incomplete",
        "problemTopic": "Sắp xếp - Tìm kiếm",
        "problemDifficulty": "1"
    },
    {
        "problemName": "SỐ NHỎ NHẤT VÀ NHỎ THỨ HAI",
        "problemLink": "https://code.ptit.edu.vn/student/question/DSA06022",
        "problemID": "DSA06022",
        "problemStatus": "Incomplete",
        "problemTopic": "Sắp xếp - Tìm kiếm",
        "problemDifficulty": "1"
    },
    {
        "problemName": "SẮP XẾP CHỌN",
        "problemLink": "https://code.ptit.edu.vn/student/question/DSA06024",
        "problemID": "DSA06024",
        "problemStatus": "Incomplete",
        "problemTopic": "Sắp xếp - Tìm kiếm",
        "problemDifficulty": "1"
    },
    {
        "problemName": "SẮP XẾP ĐỔI CHỖ TRỰC TIẾP - LIỆT KÊ NGƯỢC",
        "problemLink": "https://code.ptit.edu.vn/student/question/DSA06027",
        "problemID": "DSA06027",
        "problemStatus": "Incomplete",
        "problemTopic": "Sắp xếp - Tìm kiếm",
        "problemDifficulty": "1"
    },
    {
        "problemName": "SẮP XẾP CHÈN - LIỆT KÊ NGƯỢC",
        "problemLink": "https://code.ptit.edu.vn/student/question/DSA06029",
        "problemID": "DSA06029",
        "problemStatus": "Incomplete",
        "problemTopic": "Sắp xếp - Tìm kiếm",
        "problemDifficulty": "1"
    },
    {
        "problemName": "CẶP SỐ CÓ TỔNG BẰNG K",
        "problemLink": "https://code.ptit.edu.vn/student/question/DSA06034",
        "problemID": "DSA06034",
        "problemStatus": "Incomplete",
        "problemTopic": "Sắp xếp - Tìm kiếm",
        "problemDifficulty": "1"
    },
    {
        "problemName": "SỐ ĐẦU TIÊN BỊ LẶP",
        "problemLink": "https://code.ptit.edu.vn/student/question/DSA06039",
        "problemID": "DSA06039",
        "problemStatus": "Incomplete",
        "problemTopic": "Sắp xếp - Tìm kiếm",
        "problemDifficulty": "1"
    },
    {
        "problemName": "SỐ XUẤT HIỆN NHIỀU NHẤT",
        "problemLink": "https://code.ptit.edu.vn/student/question/DSA06041",
        "problemID": "DSA06041",
        "problemStatus": "Incomplete",
        "problemTopic": "Sắp xếp - Tìm kiếm",
        "problemDifficulty": "1"
    },
    {
        "problemName": "ĐIỂM CÂN BẰNG",
        "problemLink": "https://code.ptit.edu.vn/student/question/DSA06043",
        "problemID": "DSA06043",
        "problemStatus": "Incomplete",
        "problemTopic": "Sắp xếp - Tìm kiếm",
        "problemDifficulty": "1"
    },
    {
        "problemName": "SẮP XẾP CHẴN LẺ",
        "problemLink": "https://code.ptit.edu.vn/student/question/DSA06044",
        "problemID": "DSA06044",
        "problemStatus": "Incomplete",
        "problemTopic": "Sắp xếp - Tìm kiếm",
        "problemDifficulty": "1"
    },
    {
        "problemName": "SỐ LẦN QUAY VÒNG",
        "problemLink": "https://code.ptit.edu.vn/student/question/DSA06048",
        "problemID": "DSA06048",
        "problemStatus": "Incomplete",
        "problemTopic": "Sắp xếp - Tìm kiếm",
        "problemDifficulty": "1"
    },
    {
        "problemName": "ĐẾM CẶP",
        "problemLink": "https://code.ptit.edu.vn/student/question/DSA06049",
        "problemID": "DSA06049",
        "problemStatus": "Incomplete",
        "problemTopic": "Sắp xếp - Tìm kiếm",
        "problemDifficulty": "1"
    },
    {
        "problemName": "NGĂN XẾP 1",
        "problemLink": "https://code.ptit.edu.vn/student/question/DSA07001",
        "problemID": "DSA07001",
        "problemStatus": "Incomplete",
        "problemTopic": "Ngăn xếp",
        "problemDifficulty": "1"
    },
    {
        "problemName": "BIẾN ĐỐI TIỀN TỐ - HẬU TỐ",
        "problemLink": "https://code.ptit.edu.vn/student/question/DSA07010",
        "problemID": "DSA07010",
        "problemStatus": "Incomplete",
        "problemTopic": "Ngăn xếp",
        "problemDifficulty": "1"
    },
    {
        "problemName": "TÍNH GIÁ TRỊ BIỂU THỨC HẬU TỐ",
        "problemLink": "https://code.ptit.edu.vn/student/question/DSA07013",
        "problemID": "DSA07013",
        "problemStatus": "Incomplete",
        "problemTopic": "Ngăn xếp",
        "problemDifficulty": "1"
    },
    {
        "problemName": "TÍNH GIÁ TRỊ BIỂU THỨC TIỀN TỐ",
        "problemLink": "https://code.ptit.edu.vn/student/question/DSA07014",
        "problemID": "DSA07014",
        "problemStatus": "Incomplete",
        "problemTopic": "Ngăn xếp",
        "problemDifficulty": "1"
    },
    {
        "problemName": "DÃY NGOẶC ĐÚNG DÀI NHẤT",
        "problemLink": "https://code.ptit.edu.vn/student/question/DSA07021",
        "problemID": "DSA07021",
        "problemStatus": "Incomplete",
        "problemTopic": "Ngăn xếp",
        "problemDifficulty": "1"
    },
    {
        "problemName": "PHẦN TỬ BÊN PHẢI ĐẦU TIÊN LỚN HƠN",
        "problemLink": "https://code.ptit.edu.vn/student/question/DSA07027",
        "problemID": "DSA07027",
        "problemStatus": "Incomplete",
        "problemTopic": "Ngăn xếp",
        "problemDifficulty": "1"
    },
    {
        "problemName": "KIỂM TRA DÃY NGOẶC ĐÚNG",
        "problemLink": "https://code.ptit.edu.vn/student/question/DSA07110",
        "problemID": "DSA07110",
        "problemStatus": "Incomplete",
        "problemTopic": "Ngăn xếp",
        "problemDifficulty": "1"
    },
    {
        "problemName": "CẤU TRÚC DỮ LIỆU HÀNG ĐỢI 2",
        "problemLink": "https://code.ptit.edu.vn/student/question/DSA08002",
        "problemID": "DSA08002",
        "problemStatus": "Incomplete",
        "problemTopic": "Hàng đợi",
        "problemDifficulty": "1"
    },
    {
        "problemName": "SỐ NHỊ PHÂN TỪ 1 ĐẾN N",
        "problemLink": "https://code.ptit.edu.vn/student/question/DSA08005",
        "problemID": "DSA08005",
        "problemStatus": "Incomplete",
        "problemTopic": "Hàng đợi",
        "problemDifficulty": "1"
    },
    {
        "problemName": "SỐ 0 VÀ SỐ 9",
        "problemLink": "https://code.ptit.edu.vn/student/question/DSA08006",
        "problemID": "DSA08006",
        "problemStatus": "Incomplete",
        "problemTopic": "Hàng đợi",
        "problemDifficulty": "1"
    },
    {
        "problemName": "SỐ LỘC PHÁT 2",
        "problemLink": "https://code.ptit.edu.vn/student/question/DSA08018",
        "problemID": "DSA08018",
        "problemStatus": "Incomplete",
        "problemTopic": "Hàng đợi",
        "problemDifficulty": "1"
    },
    {
        "problemName": "DFS TRÊN ĐỒ THỊ VÔ HƯỚNG",
        "problemLink": "https://code.ptit.edu.vn/student/question/DSA09004",
        "problemID": "DSA09004",
        "problemStatus": "Incomplete",
        "problemTopic": "Duyệt đồ thị",
        "problemDifficulty": "1"
    },
    {
        "problemName": "BFS TRÊN ĐỒ THỊ VÔ HƯỚNG",
        "problemLink": "https://code.ptit.edu.vn/student/question/DSA09005",
        "problemID": "DSA09005",
        "problemStatus": "Incomplete",
        "problemTopic": "Duyệt đồ thị",
        "problemDifficulty": "1"
    },
    {
        "problemName": "LIỆT KÊ CẠNH CẦU",
        "problemLink": "https://code.ptit.edu.vn/student/question/DSA09013",
        "problemID": "DSA09013",
        "problemStatus": "Incomplete",
        "problemTopic": "Duyệt đồ thị",
        "problemDifficulty": "1"
    },
    {
        "problemName": "CHUYỂN DANH SÁCH KỀ SANG MA TRẬN KỀ",
        "problemLink": "https://code.ptit.edu.vn/student/question/DSA09020",
        "problemID": "DSA09020",
        "problemStatus": "Incomplete",
        "problemTopic": "Duyệt đồ thị",
        "problemDifficulty": "1"
    },
    {
        "problemName": "DFS TRÊN ĐỒ THỊ CÓ HƯỚNG",
        "problemLink": "https://code.ptit.edu.vn/student/question/DSA09022",
        "problemID": "DSA09022",
        "problemStatus": "Incomplete",
        "problemTopic": "Duyệt đồ thị",
        "problemDifficulty": "1"
    },
    {
        "problemName": "ĐƯỜNG ĐI THEO DFS VỚI ĐỒ THỊ CÓ HƯỚNG",
        "problemLink": "https://code.ptit.edu.vn/student/question/DSA09025",
        "problemID": "DSA09025",
        "problemStatus": "Incomplete",
        "problemTopic": "Duyệt đồ thị",
        "problemDifficulty": "1"
    },
    {
        "problemName": "ĐƯỜNG ĐI THEO BFS TRÊN ĐỒ THỊ CÓ HƯỚNG",
        "problemLink": "https://code.ptit.edu.vn/student/question/DSA09026",
        "problemID": "DSA09026",
        "problemStatus": "Incomplete",
        "problemTopic": "Duyệt đồ thị",
        "problemDifficulty": "1"
    },
    {
        "problemName": "ĐƯỜNG ĐI VÀ CHU TRÌNH EULER VỚI ĐỒ THỊ VÔ HƯỚNG",
        "problemLink": "https://code.ptit.edu.vn/student/question/DSA10004",
        "problemID": "DSA10004",
        "problemStatus": "Incomplete",
        "problemTopic": "Duyệt đồ thị",
        "problemDifficulty": "1"
    },
    {
        "problemName": "CHU TRÌNH EULER TRONG ĐỒ THỊ CÓ HƯỚNG",
        "problemLink": "https://code.ptit.edu.vn/student/question/DSA10005",
        "problemID": "DSA10005",
        "problemStatus": "Incomplete",
        "problemTopic": "Duyệt đồ thị",
        "problemDifficulty": "1"
    },
    {
        "problemName": "PHƯƠNG ÁN TỐI ƯU",
        "problemLink": "https://code.ptit.edu.vn/student/question/CTDL_003",
        "problemID": "CTDL_003",
        "problemStatus": "Incomplete",
        "problemTopic": "Sinh kế tiếp",
        "problemDifficulty": "2"
    },
    {
        "problemName": "HÀNH TRÌNH DU LỊCH - 1",
        "problemLink": "https://code.ptit.edu.vn/student/question/DSA_P029",
        "problemID": "DSA_P029",
        "problemStatus": "Incomplete",
        "problemTopic": "Quy hoạch động",
        "problemDifficulty": "2"
    },
    {
        "problemName": "XÂU AB ĐẶC BIỆT",
        "problemLink": "https://code.ptit.edu.vn/student/question/DSA01009",
        "problemID": "DSA01009",
        "problemStatus": "Incomplete",
        "problemTopic": "Sinh kế tiếp",
        "problemDifficulty": "2"
    },
    {
        "problemName": "TẬP QUÂN SỰ",
        "problemLink": "https://code.ptit.edu.vn/student/question/DSA01010",
        "problemID": "DSA01010",
        "problemStatus": "Incomplete",
        "problemTopic": "Sinh kế tiếp",
        "problemDifficulty": "2"
    },
    {
        "problemName": "MÃ GRAY 1",
        "problemLink": "https://code.ptit.edu.vn/student/question/DSA01012",
        "problemID": "DSA01012",
        "problemStatus": "Incomplete",
        "problemTopic": "Sinh kế tiếp",
        "problemDifficulty": "2"
    },
    {
        "problemName": "TẬP HỢP",
        "problemLink": "https://code.ptit.edu.vn/student/question/DSA01014",
        "problemID": "DSA01014",
        "problemStatus": "Incomplete",
        "problemTopic": "Sinh kế tiếp",
        "problemDifficulty": "2"
    },
    {
        "problemName": "DI CHUYỂN TRONG MÊ CUNG 2",
        "problemLink": "https://code.ptit.edu.vn/student/question/DSA02004",
        "problemID": "DSA02004",
        "problemStatus": "Incomplete",
        "problemTopic": "Quay lui - Nhánh cận",
        "problemDifficulty": "2"
    },
    {
        "problemName": "CHỌN SỐ TỪ MA TRẬN VUÔNG CẤP N",
        "problemLink": "https://code.ptit.edu.vn/student/question/DSA02008",
        "problemID": "DSA02008",
        "problemStatus": "Incomplete",
        "problemTopic": "Sinh kế tiếp",
        "problemDifficulty": "2"
    },
    {
        "problemName": "TỔ HỢP SỐ CÓ TỔNG BẰNG X",
        "problemLink": "https://code.ptit.edu.vn/student/question/DSA02010",
        "problemID": "DSA02010",
        "problemStatus": "Incomplete",
        "problemTopic": "Quay lui - Nhánh cận",
        "problemDifficulty": "2"
    },
    {
        "problemName": "SẮP XẾP QUÂN HẬU 2",
        "problemLink": "https://code.ptit.edu.vn/student/question/DSA02017",
        "problemID": "DSA02017",
        "problemStatus": "Incomplete",
        "problemTopic": "Quay lui - Nhánh cận",
        "problemDifficulty": "2"
    },
    {
        "problemName": "PHÉP TOÁN CƠ BẢN",
        "problemLink": "https://code.ptit.edu.vn/student/question/DSA02026",
        "problemID": "DSA02026",
        "problemStatus": "Incomplete",
        "problemTopic": "Quay lui - Nhánh cận",
        "problemDifficulty": "2"
    },
    {
        "problemName": "HOÁN VỊ CÁC CHỮ SỐ",
        "problemLink": "https://code.ptit.edu.vn/student/question/DSA02035",
        "problemID": "DSA02035",
        "problemStatus": "Incomplete",
        "problemTopic": "Quay lui - Nhánh cận",
        "problemDifficulty": "2"
    },
    {
        "problemName": "DÃY CON CÓ TỔNG LẺ",
        "problemLink": "https://code.ptit.edu.vn/student/question/DSA02036",
        "problemID": "DSA02036",
        "problemStatus": "Incomplete",
        "problemTopic": "Quay lui - Nhánh cận",
        "problemDifficulty": "2"
    },
    {
        "problemName": "DÃY CON CÓ TỔNG NGUYÊN TỐ",
        "problemLink": "https://code.ptit.edu.vn/student/question/DSA02037",
        "problemID": "DSA02037",
        "problemStatus": "Incomplete",
        "problemTopic": "Quay lui - Nhánh cận",
        "problemDifficulty": "2"
    },
    {
        "problemName": "TẬP CON CỦA XÂU KÝ TỰ",
        "problemLink": "https://code.ptit.edu.vn/student/question/DSA02045",
        "problemID": "DSA02045",
        "problemStatus": "Incomplete",
        "problemTopic": "Quay lui - Nhánh cận",
        "problemDifficulty": "2"
    },
    {
        "problemName": "SẮP XẾP CÔNG VIỆC 2",
        "problemLink": "https://code.ptit.edu.vn/student/question/DSA03009",
        "problemID": "DSA03009",
        "problemStatus": "Incomplete",
        "problemTopic": "Giải thuật tham lam",
        "problemDifficulty": "2"
    },
    {
        "problemName": "NỐI DÂY 2",
        "problemLink": "https://code.ptit.edu.vn/student/question/DSA03011",
        "problemID": "DSA03011",
        "problemStatus": "Incomplete",
        "problemTopic": "Giải thuật tham lam",
        "problemDifficulty": "2"
    },
    {
        "problemName": "PHÂN SỐ ĐƠN VỊ",
        "problemLink": "https://code.ptit.edu.vn/student/question/DSA03019",
        "problemID": "DSA03019",
        "problemStatus": "Incomplete",
        "problemTopic": "Giải thuật tham lam",
        "problemDifficulty": "2"
    },
    {
        "problemName": "SẮP XẾP VIÊN BI",
        "problemLink": "https://code.ptit.edu.vn/student/question/DSA03023",
        "problemID": "DSA03023",
        "problemStatus": "Incomplete",
        "problemTopic": "Giải thuật tham lam",
        "problemDifficulty": "2"
    },
    {
        "problemName": "LŨY THỪA MA TRẬN 1",
        "problemLink": "https://code.ptit.edu.vn/student/question/DSA04009",
        "problemID": "DSA04009",
        "problemStatus": "Incomplete",
        "problemTopic": "Chia và trị",
        "problemDifficulty": "2"
    },
    {
        "problemName": "TÍCH ĐA THỨC",
        "problemLink": "https://code.ptit.edu.vn/student/question/DSA04012",
        "problemID": "DSA04012",
        "problemStatus": "Incomplete",
        "problemTopic": "Chia và trị",
        "problemDifficulty": "2"
    },
    {
        "problemName": "TỔNG LỚN NHẤT CỦA DÃY CON TĂNG DẦN",
        "problemLink": "https://code.ptit.edu.vn/student/question/DSA05006",
        "problemID": "DSA05006",
        "problemStatus": "Incomplete",
        "problemTopic": "Quy hoạch động",
        "problemDifficulty": "2"
    },
    {
        "problemName": "TỔNG LỚN NHẤT CỦA DÃY CON KHÔNG KỀ NHAU",
        "problemLink": "https://code.ptit.edu.vn/student/question/DSA05007",
        "problemID": "DSA05007",
        "problemStatus": "Incomplete",
        "problemTopic": "Quy hoạch động",
        "problemDifficulty": "2"
    },
    {
        "problemName": "XÂU CON ĐỐI XỨNG DÀI NHẤT",
        "problemLink": "https://code.ptit.edu.vn/student/question/DSA05018",
        "problemID": "DSA05018",
        "problemStatus": "Incomplete",
        "problemTopic": "Quy hoạch động",
        "problemDifficulty": "2"
    },
    {
        "problemName": "TỔNG CÁC XÂU CON",
        "problemLink": "https://code.ptit.edu.vn/student/question/DSA05023",
        "problemID": "DSA05023",
        "problemStatus": "Incomplete",
        "problemTopic": "Quy hoạch động",
        "problemDifficulty": "2"
    },
    {
        "problemName": "TỔNG BẰNG K",
        "problemLink": "https://code.ptit.edu.vn/student/question/DSA05024",
        "problemID": "DSA05024",
        "problemStatus": "Incomplete",
        "problemTopic": "Quy hoạch động",
        "problemDifficulty": "2"
    },
    {
        "problemName": "TỔNG BÌNH PHƯƠNG",
        "problemLink": "https://code.ptit.edu.vn/student/question/DSA05031",
        "problemID": "DSA05031",
        "problemStatus": "Incomplete",
        "problemTopic": "Quy hoạch động",
        "problemDifficulty": "2"
    },
    {
        "problemName": "DÃY CON TĂNG DÀI NHẤT 2 CHIỀU",
        "problemLink": "https://code.ptit.edu.vn/student/question/DSA05038",
        "problemID": "DSA05038",
        "problemStatus": "Incomplete",
        "problemTopic": "Quy hoạch động",
        "problemDifficulty": "2"
    },
    {
        "problemName": "DÃY TAM GIÁC DÀI NHẤT",
        "problemLink": "https://code.ptit.edu.vn/student/question/DSA05040",
        "problemID": "DSA05040",
        "problemStatus": "Incomplete",
        "problemTopic": "Quy hoạch động",
        "problemDifficulty": "2"
    },
    {
        "problemName": "BIẾN ĐỔI VỀ XÂU ĐỐI XỨNG",
        "problemLink": "https://code.ptit.edu.vn/student/question/DSA05041",
        "problemID": "DSA05041",
        "problemStatus": "Incomplete",
        "problemTopic": "Quy hoạch động",
        "problemDifficulty": "2"
    },
    {
        "problemName": "DÃY CON LIÊN TIẾP TỔNG BẰNG K",
        "problemLink": "https://code.ptit.edu.vn/student/question/DSA05042",
        "problemID": "DSA05042",
        "problemStatus": "Incomplete",
        "problemTopic": "Quy hoạch động",
        "problemDifficulty": "2"
    },
    {
        "problemName": "SỐ THUẬN NGHỊCH",
        "problemLink": "https://code.ptit.edu.vn/student/question/DSA05043",
        "problemID": "DSA05043",
        "problemStatus": "Incomplete",
        "problemTopic": "Quy hoạch động",
        "problemDifficulty": "2"
    },
    {
        "problemName": "SẮP XẾP ĐOẠN CON",
        "problemLink": "https://code.ptit.edu.vn/student/question/DSA06037",
        "problemID": "DSA06037",
        "problemStatus": "Incomplete",
        "problemTopic": "Sắp xếp - Tìm kiếm",
        "problemDifficulty": "2"
    },
    {
        "problemName": "CẶP SỐ",
        "problemLink": "https://code.ptit.edu.vn/student/question/DSA06038",
        "problemID": "DSA06038",
        "problemStatus": "Incomplete",
        "problemTopic": "Sắp xếp - Tìm kiếm",
        "problemDifficulty": "2"
    },
    {
        "problemName": "BIẾN ĐỔI TRUNG TỐ - HẬU TỐ",
        "problemLink": "https://code.ptit.edu.vn/student/question/DSA07008",
        "problemID": "DSA07008",
        "problemStatus": "Incomplete",
        "problemTopic": "Ngăn xếp",
        "problemDifficulty": "2"
    },
    {
        "problemName": "BIẾN ĐỔI HẬU TỐ - TIỀN TỐ",
        "problemLink": "https://code.ptit.edu.vn/student/question/DSA07011",
        "problemID": "DSA07011",
        "problemStatus": "Incomplete",
        "problemTopic": "Ngăn xếp",
        "problemDifficulty": "2"
    },
    {
        "problemName": "BIỂU THỨC TĂNG GIẢM",
        "problemLink": "https://code.ptit.edu.vn/student/question/DSA07016",
        "problemID": "DSA07016",
        "problemStatus": "Incomplete",
        "problemTopic": "Ngăn xếp",
        "problemDifficulty": "2"
    },
    {
        "problemName": "NHỊP CHỨNG KHOÁN",
        "problemLink": "https://code.ptit.edu.vn/student/question/DSA07028",
        "problemID": "DSA07028",
        "problemStatus": "Incomplete",
        "problemTopic": "Ngăn xếp",
        "problemDifficulty": "2"
    },
    {
        "problemName": "QUÂN MÃ",
        "problemLink": "https://code.ptit.edu.vn/student/question/DSA08025",
        "problemID": "DSA08025",
        "problemStatus": "Incomplete",
        "problemTopic": "Hàng đợi",
        "problemDifficulty": "2"
    },
    {
        "problemName": "ĐƯỜNG ĐI THEO DFS VỚI ĐỒ THỊ VÔ HƯỚNG",
        "problemLink": "https://code.ptit.edu.vn/student/question/DSA09006",
        "problemID": "DSA09006",
        "problemStatus": "Incomplete",
        "problemTopic": "Duyệt đồ thị",
        "problemDifficulty": "2"
    },
    {
        "problemName": "ĐƯỜNG ĐI THEO BFS TRÊN ĐỒ THỊ VÔ HƯỚNG",
        "problemLink": "https://code.ptit.edu.vn/student/question/DSA09007",
        "problemID": "DSA09007",
        "problemStatus": "Incomplete",
        "problemTopic": "Duyệt đồ thị",
        "problemDifficulty": "2"
    },
    {
        "problemName": "TÌM SỐ THÀNH PHẦN LIÊN THÔNG VỚI BFS",
        "problemLink": "https://code.ptit.edu.vn/student/question/DSA09009",
        "problemID": "DSA09009",
        "problemStatus": "Incomplete",
        "problemTopic": "Duyệt đồ thị",
        "problemDifficulty": "2"
    },
    {
        "problemName": "KIỂM TRA TÍNH LIÊN THÔNG MẠNH",
        "problemLink": "https://code.ptit.edu.vn/student/question/DSA09010",
        "problemID": "DSA09010",
        "problemStatus": "Incomplete",
        "problemTopic": "Duyệt đồ thị",
        "problemDifficulty": "2"
    },
    {
        "problemName": "KIỂM TRA CHU TRÌNH TRÊN ĐỒ THỊ CÓ HƯỚNG VỚI DFS",
        "problemLink": "https://code.ptit.edu.vn/student/question/DSA09016",
        "problemID": "DSA09016",
        "problemStatus": "Incomplete",
        "problemTopic": "Duyệt đồ thị",
        "problemDifficulty": "2"
    },
    {
        "problemName": "KIỂM TRA ĐỒ THỊ CÓ PHẢI LÀ CÂY HAY KHÔNG",
        "problemLink": "https://code.ptit.edu.vn/student/question/DSA09017",
        "problemID": "DSA09017",
        "problemStatus": "Incomplete",
        "problemTopic": "Duyệt đồ thị",
        "problemDifficulty": "2"
    },
    {
        "problemName": "TÔ MÀU ĐỒ THỊ",
        "problemLink": "https://code.ptit.edu.vn/student/question/DSA09028",
        "problemID": "DSA09028",
        "problemStatus": "Incomplete",
        "problemTopic": "Duyệt đồ thị",
        "problemDifficulty": "2"
    },
    {
        "problemName": "ĐƯỜNG ĐI HAMILTON",
        "problemLink": "https://code.ptit.edu.vn/student/question/DSA09029",
        "problemID": "DSA09029",
        "problemStatus": "Incomplete",
        "problemTopic": "Duyệt đồ thị",
        "problemDifficulty": "2"
    },
    {
        "problemName": "KẾT BẠN",
        "problemLink": "https://code.ptit.edu.vn/student/question/DSA09032",
        "problemID": "DSA09032",
        "problemStatus": "Incomplete",
        "problemTopic": "Duyệt đồ thị",
        "problemDifficulty": "2"
    },
    {
        "problemName": "MẠNG XÃ HỘI",
        "problemLink": "https://code.ptit.edu.vn/student/question/DSA09033",
        "problemID": "DSA09033",
        "problemStatus": "Incomplete",
        "problemTopic": "Duyệt đồ thị",
        "problemDifficulty": "2"
    },
    {
        "problemName": "KIỂM TRA CHU TRÌNH SỬ DỤNG DISJOIN SET",
        "problemLink": "https://code.ptit.edu.vn/student/question/DSA10003",
        "problemID": "DSA10003",
        "problemStatus": "Incomplete",
        "problemTopic": "Duyệt đồ thị",
        "problemDifficulty": "2"
    },
    {
        "problemName": "CÂY KHUNG CỦA ĐỒ THỊ THEO THUẬT TOÁN DFS",
        "problemLink": "https://code.ptit.edu.vn/student/question/DSA10006",
        "problemID": "DSA10006",
        "problemStatus": "Incomplete",
        "problemTopic": "Đồ thị nâng cao",
        "problemDifficulty": "2"
    },
    {
        "problemName": "CÂY BIỂU THỨC 1",
        "problemLink": "https://code.ptit.edu.vn/student/question/DSA11001",
        "problemID": "DSA11001",
        "problemStatus": "Incomplete",
        "problemTopic": "Cây nhị phân",
        "problemDifficulty": "2"
    },
    {
        "problemName": "KIỂM TRA NODE LÁ",
        "problemLink": "https://code.ptit.edu.vn/student/question/DSA11008",
        "problemID": "DSA11008",
        "problemStatus": "Incomplete",
        "problemTopic": "Cây nhị phân",
        "problemDifficulty": "2"
    },
    {
        "problemName": "ĐỔI TIỀN",
        "problemLink": "https://code.ptit.edu.vn/student/question/DSAKT012",
        "problemID": "DSAKT012",
        "problemStatus": "Incomplete",
        "problemTopic": "Quay lui - Nhánh cận",
        "problemDifficulty": "2"
    },
    {
        "problemName": "CHIA MẢNG",
        "problemLink": "https://code.ptit.edu.vn/student/question/DSA02009",
        "problemID": "DSA02009",
        "problemStatus": "Incomplete",
        "problemTopic": "Quay lui - Nhánh cận",
        "problemDifficulty": "3"
    },
    {
        "problemName": "MÁY ATM",
        "problemLink": "https://code.ptit.edu.vn/student/question/DSA02011",
        "problemID": "DSA02011",
        "problemStatus": "Incomplete",
        "problemTopic": "Quay lui - Nhánh cận",
        "problemDifficulty": "3"
    },
    {
        "problemName": "NGƯỜI DU LỊCH",
        "problemLink": "https://code.ptit.edu.vn/student/question/DSA02027",
        "problemID": "DSA02027",
        "problemStatus": "Incomplete",
        "problemTopic": "Quay lui - Nhánh cận",
        "problemDifficulty": "3"
    },
    {
        "problemName": "GIÁ TRỊ LỚN NHẤT",
        "problemLink": "https://code.ptit.edu.vn/student/question/DSA03027",
        "problemID": "DSA03027",
        "problemStatus": "Incomplete",
        "problemTopic": "Giải thuật tham lam",
        "problemDifficulty": "3"
    },
    {
        "problemName": "CẶP SỐ",
        "problemLink": "https://code.ptit.edu.vn/student/question/DSA05021",
        "problemID": "DSA05021",
        "problemStatus": "Incomplete",
        "problemTopic": "Quy hoạch động",
        "problemDifficulty": "3"
    },
    {
        "problemName": "XÂU ĐỐI XỨNG 1",
        "problemLink": "https://code.ptit.edu.vn/student/question/DSA05032",
        "problemID": "DSA05032",
        "problemStatus": "Incomplete",
        "problemTopic": "Quy hoạch động",
        "problemDifficulty": "3"
    },
    {
        "problemName": "TỔNG CHỮ SỐ",
        "problemLink": "https://code.ptit.edu.vn/student/question/DSA05039",
        "problemID": "DSA05039",
        "problemStatus": "Incomplete",
        "problemTopic": "Quy hoạch động",
        "problemDifficulty": "3"
    },
    {
        "problemName": "XÂU TỐT",
        "problemLink": "https://code.ptit.edu.vn/student/question/DSA06045",
        "problemID": "DSA06045",
        "problemStatus": "Incomplete",
        "problemTopic": "Sắp xếp - Tìm kiếm",
        "problemDifficulty": "3"
    },
    {
        "problemName": "XÓA DẤU NGOẶC",
        "problemLink": "https://code.ptit.edu.vn/student/question/DSA07006",
        "problemID": "DSA07006",
        "problemStatus": "Incomplete",
        "problemTopic": "Ngăn xếp",
        "problemDifficulty": "3"
    },
    {
        "problemName": "SO SÁNH BIỂU THỨC",
        "problemLink": "https://code.ptit.edu.vn/student/question/DSA07007",
        "problemID": "DSA07007",
        "problemStatus": "Incomplete",
        "problemTopic": "Ngăn xếp",
        "problemDifficulty": "3"
    },
    {
        "problemName": "TỔNG ĐA THỨC",
        "problemLink": "https://code.ptit.edu.vn/student/question/DSA07018",
        "problemID": "DSA07018",
        "problemStatus": "Incomplete",
        "problemTopic": "Ngăn xếp",
        "problemDifficulty": "3"
    },
    {
        "problemName": "GHÉP VÁN GỖ",
        "problemLink": "https://code.ptit.edu.vn/student/question/DSA07024",
        "problemID": "DSA07024",
        "problemStatus": "Incomplete",
        "problemTopic": "Ngăn xếp",
        "problemDifficulty": "3"
    },
    {
        "problemName": "HÌNH CHỮ NHẬT 0-1",
        "problemLink": "https://code.ptit.edu.vn/student/question/DSA07030",
        "problemID": "DSA07030",
        "problemStatus": "Incomplete",
        "problemTopic": "Ngăn xếp",
        "problemDifficulty": "3"
    },
    {
        "problemName": "TÌM SỐ K THỎA MÃN ĐIỀU KIỆN",
        "problemLink": "https://code.ptit.edu.vn/student/question/DSA08012",
        "problemID": "DSA08012",
        "problemStatus": "Incomplete",
        "problemTopic": "Hàng đợi",
        "problemDifficulty": "3"
    },
    {
        "problemName": "QUAY HÌNH VUÔNG",
        "problemLink": "https://code.ptit.edu.vn/student/question/DSA08029",
        "problemID": "DSA08029",
        "problemStatus": "Incomplete",
        "problemTopic": "Hàng đợi",
        "problemDifficulty": "3"
    },
    {
        "problemName": "LAN TRUYỀN DINH DƯỠNG",
        "problemLink": "https://code.ptit.edu.vn/student/question/DSA09049",
        "problemID": "DSA09049",
        "problemStatus": "Incomplete",
        "problemTopic": "Duyệt đồ thị",
        "problemDifficulty": "3"
    },
    {
        "problemName": "CÂY NHỊ PHÂN HOÀN HẢO",
        "problemLink": "https://code.ptit.edu.vn/student/question/DSA11010",
        "problemID": "DSA11010",
        "problemStatus": "Incomplete",
        "problemTopic": "Cây nhị phân",
        "problemDifficulty": "3"
    },
    {
        "problemName": "CÂY NHỊ PHÂN ĐỦ",
        "problemLink": "https://code.ptit.edu.vn/student/question/DSA11011",
        "problemID": "DSA11011",
        "problemStatus": "Incomplete",
        "problemTopic": "Cây nhị phân",
        "problemDifficulty": "3"
    },
    {
        "problemName": "CÂY NHỊ PHÂN BẰNG NHAU",
        "problemLink": "https://code.ptit.edu.vn/student/question/DSA11012",
        "problemID": "DSA11012",
        "problemStatus": "Incomplete",
        "problemTopic": "Cây nhị phân",
        "problemDifficulty": "3"
    },
    {
        "problemName": "TỔNG NODE LÁ BÊN PHẢI",
        "problemLink": "https://code.ptit.edu.vn/student/question/DSA11014",
        "problemID": "DSA11014",
        "problemStatus": "Incomplete",
        "problemTopic": "Cây nhị phân",
        "problemDifficulty": "3"
    },
    {
        "problemName": "BIẾN ĐỔI SANG CÂY NHỊ PHÂN TÌM KIẾM",
        "problemLink": "https://code.ptit.edu.vn/student/question/DSA11016",
        "problemID": "DSA11016",
        "problemStatus": "Incomplete",
        "problemTopic": "Cây nhị phân",
        "problemDifficulty": "3"
    },
    {
        "problemName": "DUYỆT CÂY NHỊ PHÂN TÌM KIẾM 1",
        "problemLink": "https://code.ptit.edu.vn/student/question/DSA11017",
        "problemID": "DSA11017",
        "problemStatus": "Incomplete",
        "problemTopic": "Cây nhị phân",
        "problemDifficulty": "3"
    },
    {
        "problemName": "XÂY DỰNG LẠI CÂY NHỊ PHÂN TÌM KIẾM",
        "problemLink": "https://code.ptit.edu.vn/student/question/DSA11018",
        "problemID": "DSA11018",
        "problemStatus": "Incomplete",
        "problemTopic": "Cây nhị phân",
        "problemDifficulty": "3"
    },
    {
        "problemName": "DUYỆT CÂY NHỊ PHÂN TÌM KIẾM 2",
        "problemLink": "https://code.ptit.edu.vn/student/question/DSA11019",
        "problemID": "DSA11019",
        "problemStatus": "Incomplete",
        "problemTopic": "Cây nhị phân",
        "problemDifficulty": "3"
    },
    {
        "problemName": "NODE TRUNG GIAN CỦA CÂY NHỊ PHÂN TÌM KIẾM",
        "problemLink": "https://code.ptit.edu.vn/student/question/DSA11022",
        "problemID": "DSA11022",
        "problemStatus": "Incomplete",
        "problemTopic": "Cây nhị phân",
        "problemDifficulty": "3"
    },
    {
        "problemName": "ĐỘ SÂU CÂY NHỊ PHÂN TÌM KIẾM",
        "problemLink": "https://code.ptit.edu.vn/student/question/DSA11023",
        "problemID": "DSA11023",
        "problemStatus": "Incomplete",
        "problemTopic": "Cây nhị phân",
        "problemDifficulty": "3"
    },
    {
        "problemName": "CÂY NHỊ PHÂN TÌM KIẾM CÂN BẰNG 1",
        "problemLink": "https://code.ptit.edu.vn/student/question/DSA11024",
        "problemID": "DSA11024",
        "problemStatus": "Incomplete",
        "problemTopic": "Cây nhị phân",
        "problemDifficulty": "3"
    },
    {
        "problemName": "HÀNH TRÌNH DU LỊCH - 2",
        "problemLink": "https://code.ptit.edu.vn/student/question/DSA_P035",
        "problemID": "DSA_P035",
        "problemStatus": "Incomplete",
        "problemTopic": "Quy hoạch động",
        "problemDifficulty": "4"
    },
    {
        "problemName": "KÝ TỰ ĐẶC BIỆT",
        "problemLink": "https://code.ptit.edu.vn/student/question/DSA02021",
        "problemID": "DSA02021",
        "problemStatus": "Incomplete",
        "problemTopic": "Quay lui - Nhánh cận",
        "problemDifficulty": "4"
    },
    {
        "problemName": "TÍNH TOÁN GIÁ TRỊ BIỂU THỨC TRUNG TỐ",
        "problemLink": "https://code.ptit.edu.vn/student/question/DSA07015",
        "problemID": "DSA07015",
        "problemStatus": "Incomplete",
        "problemTopic": "Ngăn xếp",
        "problemDifficulty": "4"
    },
    {
        "problemName": "DI CHUYỂN TRÁNH VẬT CẢN",
        "problemLink": "https://code.ptit.edu.vn/student/question/DSA08013",
        "problemID": "DSA08013",
        "problemStatus": "Incomplete",
        "problemTopic": "Hàng đợi",
        "problemDifficulty": "4"
    },
    {
        "problemName": "GIEO MẦM",
        "problemLink": "https://code.ptit.edu.vn/student/question/DSA08014",
        "problemID": "DSA08014",
        "problemStatus": "Incomplete",
        "problemTopic": "Hàng đợi",
        "problemDifficulty": "4"
    },
    {
        "problemName": "DI CHUYỂN TRONG KHÔNG GIAN",
        "problemLink": "https://code.ptit.edu.vn/student/question/DSA08015",
        "problemID": "DSA08015",
        "problemStatus": "Incomplete",
        "problemTopic": "Hàng đợi",
        "problemDifficulty": "4"
    },
    {
        "problemName": "KHOẢNG CÁCH GIỮA HAI NODE",
        "problemLink": "https://code.ptit.edu.vn/student/question/DSA11030",
        "problemID": "DSA11030",
        "problemStatus": "Incomplete",
        "problemTopic": "Cây nhị phân",
        "problemDifficulty": "4"
    },
    {
        "problemName": "HEXGAME",
        "problemLink": "https://code.ptit.edu.vn/student/question/DSA08016",
        "problemID": "DSA08016",
        "problemStatus": "Incomplete",
        "problemTopic": "Hàng đợi",
        "problemDifficulty": "5"
    }
]